Workbook

Sheet Risk Register
A1: I-Property: Rental Property Management System
A2: PROJECT RISK REGISTER | Version 1.0 | Based on SRS v3.0
A4: Risk ID | B4: Category | C4: Risk Title | D4: Description | E4: SRS Reference | F4: Probability (1-5) | G4: Impact (1-5) | H4: Risk Score (P×I) | I4: Severity | J4: Mitigation Strategy | K4: Contingency Plan | L4: Risk Owner | M4: Status | N4: Target Resolution Date | O4: Residual Probability | P4: Residual Impact
A5: R-001 | B5: Integration | C5: Oracle Financial API Unavailability | D5: Oracle Financial APIs or batch interfaces may not be available or finalized in time. i-Property depends on these for payment batch transmission and expense accrual posting. Any delay or schema mismatch directly blocks Finance from processing payments. | E5: SRS §8.3, IDD-001 | F5: 3 | G5: 4 | H5: =F5*G5 -> 12 | I5: =IF(H5>=16,"Critical",IF(H5>=9,"High",IF(H5>=4,"Medium","Low"))) -> High | J5: Engage the Oracle Financial technical team early to confirm API availability and obtain finalized schemas. Define a batch file fallback (CSV/SFTP) as an interim integration method. Build retry logic with exponential backoff (3 retries at 10-minute intervals) and System Admin alerting into the integration layer. | K5: Activate the manual CSV export from i-Property and instruct Finance to import directly into Oracle Financial until the API is restored. Document the manual procedure in DP-001 Section 6. | L5: Integration Architect | M5: Open | N5: 2025-07-01 | O5: 2 | P5: 2
A6: R-002 | B6: Integration | C6: Oracle Financial Schema Mismatch on Payment Batch | D6: Field mappings between i-Property payment batch payload and Oracle Financial's expected schema may not align, causing OF 400 errors on batch transmission. This would block payment releases for the affected month. | E6: SRS §8.3, IDD-001 §3.1 | F6: 3 | G6: 5 | H6: =F6*G6 -> 15 | I6: =IF(H6>=16,"Critical",IF(H6>=9,"High",IF(H6>=4,"Medium","Low"))) -> High | J6: Conduct a field mapping workshop with the Finance and Oracle Financial teams before development begins. Document all mappings in IDD-001 Table 2. Implement a sandbox integration environment for end-to-end testing before go-live. Add schema validation on the i-Property side before transmitting. | K6: Halt payment batch transmission. System Admin and Finance are alerted per the OF 400 error handling spec. The BA and Integration Architect resolve the schema discrepancy and deploy a hotfix. Finance is notified of the delay and given an estimated resolution time. | L6: Integration Architect | M6: Open | N6: 2025-07-15 | O6: 1 | P6: 3
A7: R-003 | B7: Technical | C7: PDF Generation Engine Failure or Timeout | D7: The Approval Summary PDF engine may fail or exceed the 10-second SLA defined in FR-NR-04. This blocks the Print Queue (SCR-11) and prevents Area Admin from printing the agreement package, stalling the post-completion process. | E7: SRS §6.3, FR-NR-04 | F7: 2 | G7: 3 | H7: =F7*G7 -> 6 | I7: =IF(H7>=16,"Critical",IF(H7>=9,"High",IF(H7>=4,"Medium","Low"))) -> Medium | J7: Select a proven PDF generation library during architecture design. Define a polling mechanism (HTTP 202 with poll_url) for timeouts as specified in ERR-PDF-04-001. Implement a FAILED state alert to System Admin. Include PDF generation in load testing at P95 under 100 concurrent users. | K7: System Admin is alerted automatically. Area Admin is shown a user-friendly message with a log reference ID. IT Support manually regenerates the PDF via an admin endpoint. The print package is delivered to Area Admin as soon as generation succeeds. | L7: Development Lead | M7: Open | N7: 2025-08-01 | O7: 1 | P7: 2
A8: R-004 | B8: Technical | C8: Concurrent Submission Race Condition on Reference ID | D8: Under high concurrency, two Area Officers submitting requests simultaneously could theoretically receive duplicate reference IDs if the DB sequence object is not correctly implemented. FR-NR-01 mandates globally unique IDs using a DB sequence. | E8: SRS §6.1, FR-NR-01 TC-001-D | F8: 2 | G8: 4 | H8: =F8*G8 -> 8 | I8: =IF(H8>=16,"Critical",IF(H8>=9,"High",IF(H8>=4,"Medium","Low"))) -> Medium | J8: Use a database-native sequence object (e.g., PostgreSQL SEQUENCE) for reference ID generation. Never generate IDs in application code. Include concurrency test TC-001-D (50 simultaneous submissions) in TP-001 before UAT. Validate uniqueness constraint on the reference_id column in DB. | K8: If duplicates are detected in production, immediately freeze new submissions and audit the requests table. Apply a hotfix to the sequence logic and re-sequence affected records. Communicate impacted users with corrected reference IDs. | L8: Development Lead | M8: Open | N8: 2025-08-01 | O8: 1 | P8: 1
A9: R-005 | B9: Technical | C9: Optimistic Locking Failures on Concurrent Approvals | D9: Two approvers acting on the same request simultaneously could cause version conflicts. The PATCH /requests endpoint uses a version integer for optimistic locking. Poorly handled version mismatches result in lost updates or confusing error messages to approvers. | E9: SRS §8.1, PATCH /requests | F9: 2 | G9: 3 | H9: =F9*G9 -> 6 | I9: =IF(H9>=16,"Critical",IF(H9>=9,"High",IF(H9>=4,"Medium","Low"))) -> Medium | J9: Enforce optimistic locking on all PATCH operations. Return HTTP 409 with a clear message directing the user to refresh and retry. Test concurrent approval scenarios (TC-002-D equivalent for simultaneous actions) in TP-001. Display the version conflict message in plain language on the UI. | K9: The second approver sees a 409 error and refreshes. The request detail page reloads with the latest state. No data is lost. Monitor for repeated 409 occurrences in production logs which may indicate a process issue with multiple approvers assigned to the same area. | L9: Development Lead | M9: Open | N9: 2025-08-15 | O9: 1 | P9: 2
A10: R-006 | B10: Security | C10: Unauthorized Cross-Area Data Access | D10: An Area Officer or Admin from one area may attempt to access or modify requests, agreements, or reports belonging to another area. NFR-04 requires RBAC enforced at the API level, not only in the UI. A UI-only control is bypassable via direct API calls. | E10: SRS §11 NFR-04, §4.2 | F10: 2 | G10: 5 | H10: =F10*G10 -> 10 | I10: =IF(H10>=16,"Critical",IF(H10>=9,"High",IF(H10>=4,"Medium","Low"))) -> High | J10: Implement RBAC at the API endpoint level on every request. Area filtering must be applied server-side before any data is returned. Build and execute the full role-based test matrix from NFR-04 covering all 7 roles against all 13 screen endpoints. Include cross-area tests (e.g., Area Officer USR-A accessing AREA-B data) in TP-001 Section 5. | K10: On detection of a cross-area access attempt: audit_log captures the user ID, IP, and timestamp. System Admin is alerted. The user account is temporarily suspended pending review. IT Security conducts an access audit and confirms no data was compromised. | L10: Solution Architect | M10: Open | N10: 2025-08-15 | O10: 1 | P10: 2
A11: R-007 | B11: Security | C11: Sensitive Data Exposure in Logs or API Responses | D11: Bank account numbers and IBAN fields must never appear in application logs, API responses (unmasked), or client-side storage. NFR-05 requires AES-256 encryption at rest and masking to last 4 digits in all API responses. A development oversight could lead to a data breach. | E11: SRS §11 NFR-05, §10.3 | F11: 2 | G11: 5 | H11: =F11*G11 -> 10 | I11: =IF(H11>=16,"Critical",IF(H11>=9,"High",IF(H11>=4,"Medium","Low"))) -> High | J11: Define a data classification policy before development begins. Annotate bank_account_no and iban as sensitive fields in the data model. Implement an automated log scanner in the CI/CD pipeline that fails the build if sensitive patterns (account numbers, IBANs) are detected in logs. Conduct an API response audit (as per NFR-05 verification) before go-live. | K11: If a breach is suspected: immediately rotate all API keys and invalidate active sessions. Engage the Head of Legal and Head of Internal Audit. Conduct a forensic log audit. Notify affected landlords per regulatory requirements. Document the incident and remediation steps. | L11: Solution Architect | M11: Open | N11: 2025-07-15 | O11: 1 | P11: 3
A12: R-008 | B12: Security | C12: JWT Token Compromise or Session Hijacking | D12: JWT tokens with an 8-hour expiry could be intercepted if TLS is not properly enforced or if tokens are stored insecurely client-side. A compromised token grants the attacker full access for the token's remaining lifetime. | E12: SRS §5.2, §11 NFR-03 | F12: 2 | G12: 4 | H12: =F12*G12 -> 8 | I12: =IF(H12>=16,"Critical",IF(H12>=9,"High",IF(H12>=4,"Medium","Low"))) -> Medium | J12: Enforce HTTPS with TLS 1.2 minimum on all endpoints (HTTP redirected to HTTPS per NFR-05). Store JWT only in memory or HttpOnly cookies, never in localStorage. Implement a token revocation list for logout and account lockout events. Include JWT penetration tests in the security testing phase. | K12: On suspected token compromise: the System Admin revokes the token via the token revocation list. The affected user is forced to re-authenticate. Audit logs are reviewed to identify any actions taken under the compromised token. Affected records are flagged for review. | L12: Solution Architect | M12: Open | N12: 2025-08-01 | O12: 1 | P12: 2
A13: R-009 | B13: Data Integrity | C13: Audit Log Tampering or Deletion | D13: NFR-06 requires that the audit_log table permits no UPDATE or DELETE at the DB level. If this DB-role enforcement is not correctly configured, audit logs could be modified or deleted, compromising the organization's compliance and forensic capabilities. | E13: SRS §5.3, §11 NFR-06 | F13: 2 | G13: 5 | H13: =F13*G13 -> 10 | I13: =IF(H13>=16,"Critical",IF(H13>=9,"High",IF(H13>=4,"Medium","Low"))) -> High | J13: Enforce audit_log immutability at the database role level before go-live. The application database user must not have UPDATE or DELETE privileges on the audit_log table. Include a verification step in the deployment checklist: attempt DELETE as the application DB user and confirm permission denied (as specified in NFR-06 verification). | K13: If tampering is detected: engage Head of Internal Audit immediately. Restore audit logs from the offsite backup. Conduct a full access review to identify how the tamper was possible. Escalate to Legal if regulatory reporting is required. | L13: Database Architect | M13: Open | N13: 2025-08-01 | O13: 1 | P13: 2
A14: R-010 | B14: Data Integrity | C14: Duplicate Utility Bill Submissions Not Caught | D14: The duplicate check in FR-UT-01 (same agreement + bill_type + billing_period with status not REJECTED) must be implemented correctly. A missed duplicate could result in double payment by Finance, causing financial loss. | E14: SRS §6.7, FR-UT-01 ERR-UT-01-003 | F14: 2 | G14: 4 | H14: =F14*G14 -> 8 | I14: =IF(H14>=16,"Critical",IF(H14>=9,"High",IF(H14>=4,"Medium","Low"))) -> Medium | J14: Implement the duplicate check as a server-side query before inserting any utility bill record. Add a unique composite index on (agreement_id, bill_type, billing_period) in the DB for records where status is not REJECTED. Include test TC-008-B (same bill submitted twice) as a regression test in every release cycle. | K14: If a duplicate payment is identified post-approval: Finance is notified immediately to halt the Oracle Financial payment for the duplicate entry. The duplicate utility bill record is marked as REJECTED with an audit note. Finance and ABH are notified of the correction. | L14: Development Lead | M14: Open | N14: 2025-08-15 | O14: 1 | P14: 1
A15: R-011 | B15: Workflow | C15: Approval SLA Breach with No Escalation | D15: If a request sits in PENDING_ABH, PENDING_DIRECTOR, or PENDING_ADMIN_HO beyond the configured SLA threshold and NE-14 fails to fire, the request stalls silently. This blocks downstream Finance payment processing and agreement activation. | E15: SRS §12 NE-14, §11 NFR-01 | F15: 3 | G15: 3 | H15: =F15*G15 -> 9 | I15: =IF(H15>=16,"Critical",IF(H15>=9,"High",IF(H15>=4,"Medium","Low"))) -> High | J15: Implement the SLA breach notification (NE-14) as a scheduled job that runs every 30 minutes. Test the job in the staging environment with a shortened SLA threshold. Configure the SCR-04 Approval Queue to highlight rows in red when the SLA is breached (Days Pending column per the UI spec). Set default SLA thresholds per stage before UAT. | K15: System Admin manually escalates the stalled request to the relevant manager. The BA reviews the queue daily during the first 3 months post go-live. SLA thresholds are reviewed and adjusted after the first month of production data. | L15: BA / PMO | M15: Open | N15: 2025-09-01 | O15: 2 | P15: 2
A16: R-012 | B16: Workflow | C16: Vacated Payment Stop Not Executed Atomically | D16: FR-VT-01 requires that the payment stop flag, the audit log entry, and the Finance notification (NE-10) all execute within a single database transaction. If the transaction is not atomic and a partial failure occurs, Finance may not be notified while the payment_stopped flag is not set, leading to continued erroneous payments. | E16: SRS §6.6, FR-VT-01 ERR-VT-01-001 | F16: 2 | G16: 5 | H16: =F16*G16 -> 10 | I16: =IF(H16>=16,"Critical",IF(H16>=9,"High",IF(H16>=4,"Medium","Low"))) -> High | J16: Implement the vacated payment stop as a single ACID-compliant database transaction wrapping all three operations. Write a specific integration test (TC-007-D) that simulates a DB failure mid-transaction and verifies complete rollback: payment_stopped remains false and Finance is not notified. Deploy this test as a mandatory regression test. | K16: If a partial failure is detected: System Admin receives an automated alert per ERR-VT-01-001. Manual intervention procedure documented in DP-001 Section 6 is followed. Finance is contacted directly via phone to confirm the stop payment. The BA confirms the payment_stopped flag is correctly set before the next payment scheduler run. | L16: Development Lead | M16: Open | N16: 2025-08-01 | O16: 1 | P16: 2
... A39: R-035 | B39: Regulatory | C39: Advance Tax Withholding Reporting Obligations | D39: i-Property captures advance tax on utility bills (SRS Section 10.2) and calculates tax deductions on monthly rental payments (SRS Section 6.5). Depending on applicable tax law, the organization may be required to submit periodic advance tax withholding returns to the tax authority listing all landlords and amounts withheld. If this reporting obligation is not built into the system, the organization faces penalties for late or inaccurate tax filings. | E39: SRS §6.5, §10.2 advance_tax, §9.6 FR-RP-02 | F39: 3 | G39: 3 | H39: =F39*G39 -> 9 | I39: =IF(H39>=16,"Critical",IF(H39>=9,"High",IF(H39>=4,"Medium","Low"))) -> High | J39: Engage Finance and Head of Legal to confirm the organization's advance tax withholding reporting obligations and filing frequency (monthly, quarterly, or annually) before the Reports module is developed. Design the FR-RP-02 expense recording report to include an advance tax withholding summary in a format compatible with regulatory filing requirements. Confirm whether Oracle Financial handles tax filing submissions or whether i-Property must produce a separate regulatory report. | K39: If a tax reporting obligation is identified post-development: the BA raises a Change Request to add a regulatory tax withholding report to the Reports module (SCR-10). Finance provides the required report format and the applicable tax authority submission template. The development team implements the report in the next release cycle. Finance files the current period return manually using exported data from SCR-10 as an interim measure. | L39: BA / PMO | M39: Open | N39: 2025-07-15 | O39: 2 | P39: 2

Sheet Risk Summary
A1: RISK SUMMARY DASHBOARD — I-Property System
A2: Auto-calculated from Risk Register sheet. Do not edit cells containing formulas.
A4: Total Risks Identified | B4: =35 -> 35 | D4: Risks by Category | E4: Count | G4: PROBABILITY × IMPACT MATRIX (count of risks per cell)
A5: Critical (Score ≥ 16) | B5: =COUNTIF('Risk Register'!H5:H39,">=16") -> 0 | D5: Integration | E5: =COUNTIF('Risk Register'!B5:B39,D5) -> 2 | G5: P \ I → | H5: 1 | I5: 2 | J5: 3 | K5: 4 | L5: 5
A6: High (Score 9–15) | B6: =COUNTIFS('Risk Register'!H5:H39,">=9",'Risk Register'!H5:H39,"<=15") -> 18 | D6: Technical | E6: =COUNTIF('Risk Register'!B5:B39,D6) -> 4 | G6: 5 | H6: =COUNTIFS('Risk Register'!F5:F39,5,'Risk Register'!G5:G39,1) -> 0 | I6: =COUNTIFS('Risk Register'!F5:F39,5,'Risk Register'!G5:G39,2) -> 0 | J6: =COUNTIFS('Risk Register'!F5:F39,5,'Risk Register'!G5:G39,3) -> 0 | K6: =COUNTIFS('Risk Register'!F5:F39,5,'Risk Register'!G5:G39,4) -> 0 | L6: =COUNTIFS('Risk Register'!F5:F39,5,'Risk Register'!G5:G39,5) -> 0
A7: Medium (Score 4–8) | B7: =COUNTIFS('Risk Register'!H5:H39,">=4",'Risk Register'!H5:H39,"<=8") -> 17 | D7: Security | E7: =COUNTIF('Risk Register'!B5:B39,D7) -> 3 | G7: 4 | H7: =COUNTIFS('Risk Register'!F5:F39,4,'Risk Register'!G5:G39,1) -> 0 | I7: =COUNTIFS('Risk Register'!F5:F39,4,'Risk Register'!G5:G39,2) -> 0 | J7: =COUNTIFS('Risk Register'!F5:F39,4,'Risk Register'!G5:G39,3) -> 0 | K7: =COUNTIFS('Risk Register'!F5:F39,4,'Risk Register'!G5:G39,4) -> 0 | L7: =COUNTIFS('Risk Register'!F5:F39,4,'Risk Register'!G5:G39,5) -> 0
A8: Low (Score < 4) | B8: =COUNTIF('Risk Register'!H5:H39,"<4") -> 0 | D8: Data Integrity | E8: =COUNTIF('Risk Register'!B5:B39,D8) -> 2 | G8: 3 | H8: =COUNTIFS('Risk Register'!F5:F39,3,'Risk Register'!G5:G39,1) -> 0 | I8: =COUNTIFS('Risk Register'!F5:F39,3,'Risk Register'!G5:G39,2) -> 0 | J8: =COUNTIFS('Risk Register'!F5:F39,3,'Risk Register'!G5:G39,3) -> 5 | K8: =COUNTIFS('Risk Register'!F5:F39,3,'Risk Register'!G5:G39,4) -> 7 | L8: =COUNTIFS('Risk Register'!F5:F39,3,'Risk Register'!G5:G39,5) -> 1
A9: Open | B9: =COUNTIF('Risk Register'!M5:M39,"Open") -> 35 | D9: Workflow | E9: =COUNTIF('Risk Register'!B5:B39,D9) -> 4 | G9: 2 | H9: =COUNTIFS('Risk Register'!F5:F39,2,'Risk Register'!G5:G39,1) -> 0 | I9: =COUNTIFS('Risk Register'!F5:F39,2,'Risk Register'!G5:G39,2) -> 2 | J9: =COUNTIFS('Risk Register'!F5:F39,2,'Risk Register'!G5:G39,3) -> 6 | K9: =COUNTIFS('Risk Register'!F5:F39,2,'Risk Register'!G5:G39,4) -> 9 | L9: =COUNTIFS('Risk Register'!F5:F39,2,'Risk Register'!G5:G39,5) -> 5
A10: In Progress | B10: =COUNTIF('Risk Register'!M5:M39,"In Progress") -> 0 | D10: Notification | E10: =COUNTIF('Risk Register'!B5:B39,D10) -> 2 | G10: 1 | H10: =COUNTIFS('Risk Register'!F5:F39,1,'Risk Register'!G5:G39,1) -> 0 | I10: =COUNTIFS('Risk Register'!F5:F39,1,'Risk Register'!G5:G39,2) -> 0 | J10: =COUNTIFS('Risk Register'!F5:F39,1,'Risk Register'!G5:G39,3) -> 0 | K10: =COUNTIFS('Risk Register'!F5:F39,1,'Risk Register'!G5:G39,4) -> 0 | L10: =COUNTIFS('Risk Register'!F5:F39,1,'Risk Register'!G5:G39,5) -> 0
A11: Closed | B11: =COUNTIF('Risk Register'!M5:M39,"Closed") -> 0 | D11: Performance | E11: =COUNTIF('Risk Register'!B5:B39,D11) -> 2
D12: Requirements | E12: =COUNTIF('Risk Register'!B5:B39,D12) -> 3 | G12: Legend:
D13: Project Delivery | E13: =COUNTIF('Risk Register'!B5:B39,D13) -> 3 | H13: Critical (≥16) | I13: High (9–15) | J13: Medium (4–8) | K13: Low (<4)
D14: System | E14: =COUNTIF('Risk Register'!B5:B39,D14) -> 6
D15: Regulatory | E15: =COUNTIF('Risk Register'!B5:B39,D15) -> 4

Sheet Scoring Guide
A1: RISK SCORING GUIDE — I-Property Project
A2: Probability and Impact are rated 1 to 5. Risk Score = Probability × Impact.
A3: PROBABILITY SCALE | E3: IMPACT SCALE
A4: Score | B4: Likelihood | C4: Description | E4: Score | F4: Impact Level | G4: Description
A5: 5 | B5: Almost Certain | C5: Expected to occur in most circumstances (>80% probability) | E5: 5 | F5: Critical | G5: System-wide failure, major financial loss, regulatory breach, or reputational damage
A6: 4 | B6: Likely | C6: Will probably occur in most circumstances (60–80%) | E6: 4 | F6: Major | G6: Significant disruption to core workflows, payment processing blocked, or data breach
A7: 3 | B7: Possible | C7: Might occur at some point (40–60%) | E7: 3 | F7: Moderate | G7: Noticeable delay to go-live or operations, workaround required, moderate effort to fix
A8: 2 | B8: Unlikely | C8: Could occur in some circumstances (20–40%) | E8: 2 | F8: Minor | G8: Small disruption, easily resolved, minimal impact on timeline or stakeholders
A9: 1 | B9: Rare | C9: May only occur in exceptional circumstances (<20%) | E9: 1 | F9: Negligible | G9: Trivial impact, can be managed within normal operations with no schedule impact
A11: SEVERITY CLASSIFICATION
A12: Score Range | B12: Severity | C12: Response Required | D12: Review Frequency
A13: 16–25 | B13: Critical | C13: Immediate escalation to Project Manager and Sponsor. Mitigation must be actioned within 24 hours. | D13: Daily until resolved
A14: 9–15 | B14: High | C14: Project Manager must review within 48 hours. Mitigation plan must be defined and assigned. | D14: Weekly
A15: 4–8 | B15: Medium | C15: BA tracks in weekly status report. Risk Owner monitors and updates status. | D15: Fortnightly
A16: 1–3 | B16: Low | C16: Accepted risk. Monitor passively. Review at monthly risk review meeting. | D16: Monthly
